GeneralFunctions.py
IntermediateImageGenerate.py
PostProcess.py
__init__.py
preprocess.py
segmentation.py
BCM3D-2.0.1.dist-info/METADATA
BCM3D-2.0.1.dist-info/WHEEL
BCM3D-2.0.1.dist-info/top_level.txt
BCM3D-2.0.1.dist-info/RECORD
