Metadata-Version: 2.1
Name: BCM3D
Version: 2.0.1
Summary: BCM3D 2.0: Accurate segmentation of single bacterialcells in dense biofilms using computationallygenerated intermediate image representations
Author-email: GahlmannLab <yw9et@virginia.com>
Project-URL: Homepage, https://github.com/GahlmannLab/BCM3D-2.0
Classifier: License :: OSI Approved :: MIT License
Classifier: Programming Language :: Python
Classifier: Programming Language :: Python :: 3
Requires-Python: >=3.8
Requires-Dist: csbdeep (>=0.7.2)
Requires-Dist: scikit-image (>=0.19.3)
